eia/__init__.py
eia/crude_oil/__init__.py
eia/crude_oil/consumption_sales.py
eia/crude_oil/import_export.py
eia/crude_oil/movements.py
eia/crude_oil/pricing.py
eia/crude_oil/production.py
eia/crude_oil/refining_processing.py
eia/crude_oil/stocks.py
eia/db/__init__.py
eia/db/mssql.py
eia/db/odin_db.py
eia/utils/__init__.py
eia/utils/aws_resources.py
eia/utils/browser.py
eia/utils/constants.py
eia/utils/credentials.py
eia/utils/facets.py
eia/utils/odin_wikipedia.py
eia/utils/redis_cache.py
eia/utils/tools.py
images/__init__.py
eia_odin_pkg_rioatmadja2018-0.1.1693189414.dist-info/METADATA
eia_odin_pkg_rioatmadja2018-0.1.1693189414.dist-info/WHEEL
eia_odin_pkg_rioatmadja2018-0.1.1693189414.dist-info/top_level.txt
eia_odin_pkg_rioatmadja2018-0.1.1693189414.dist-info/zip-safe
eia_odin_pkg_rioatmadja2018-0.1.1693189414.dist-info/RECORD
