Metadata-Version: 2.1
Name: eia-odin-pkg-rioatmadja2018
Version: 0.1.1693189414
Summary: Python Wheels to interact with the EIA APIs
Home-page: UNKNOWN
Author: Rio Atmadja
Author-email: rioatmadja2018@gmail.com
License: UNKNOWN
Platform: UNKNOWN
Classifier: Programming Language :: Python :: 3
Classifier: Operating System :: OS Independent
Classifier: Intended Audience :: Developers
Requires-Python: >=3.8
Requires-Dist: redis
Requires-Dist: pandas
Requires-Dist: boto3
Requires-Dist: botocore
Requires-Dist: sqlalchemy
Requires-Dist: pymysql
Requires-Dist: sklearn-pandas
